wassncplot/__init.py
wassncplot/__main__.py
wassncplot/wassncplot.py
wassncplot/wassncplot2.py
wassncplot/WaveFieldVisualize/__init__.py
wassncplot/WaveFieldVisualize/waveview2.py
wassncplot-2.5.3.dist-info/METADATA
wassncplot-2.5.3.dist-info/WHEEL
wassncplot-2.5.3.dist-info/entry_points.txt
wassncplot-2.5.3.dist-info/top_level.txt
wassncplot-2.5.3.dist-info/RECORD
