Metadata-Version: 2.1
Name: wassncplot
Version: 2.5.3
Summary: WASSncplot is a small tool to plot NetCDF 3D data generated with WASS on top of the original image files.
Author: Filippo Bergamasco
Author-email: filippo.bergamasco@unive.it
License: GPL3
Project-URL: repository, https://github.com/fbergama/wassncplot
Keywords: WASS
Classifier: Programming Language :: Python :: 3
Classifier: Development Status :: 4 - Beta
Requires-Python: >=3.9
Requires-Dist: numpy
Requires-Dist: scipy
Requires-Dist: pyopengl
Requires-Dist: matplotlib
Requires-Dist: vispy
Requires-Dist: tqdm
Requires-Dist: opencv-python >=4.0
Requires-Dist: netcdf4
Requires-Dist: PyQt6 ; platform_system != "Linux"
